hdl/admo_defs.v
/*******************************************************************************

MIT License

Copyright (c) 2021 Gustavo Ale

Permission is hereby granted, free of charge, to any person obtaining a copy
of this software and associated documentation files (the "Software"), to deal
in the Software without restriction, including without limitation the rights
to use, copy, modify, merge, publish, distribute, sublicense, and/or sell
copies of the Software, and to permit persons to whom the Software is
furnished to do so, subject to the following conditions:

The above copyright notice and this permission notice shall be included in all
copies or substantial portions of the Software.

THE SOFTWARE IS PROVIDED "AS IS", WITHOUT WARRANTY OF ANY KIND, EXPRESS OR
IMPLIED, INCLUDING BUT NOT LIMITED TO THE WARRANTIES OF MERCHANTABILITY,
FITNESS FOR A PARTICULAR PURPOSE AND NONINFRINGEMENT. IN NO EVENT SHALL THE
AUTHORS OR COPYRIGHT HOLDERS BE LIABLE FOR ANY CLAIM, DAMAGES OR OTHER
LIABILITY, WHETHER IN AN ACTION OF CONTRACT, TORT OR OTHERWISE, ARISING FROM,
OUT OF OR IN CONNECTION WITH THE SOFTWARE OR THE USE OR OTHER DEALINGS IN THE
SOFTWARE.

*******************************************************************************/

//**************************************
// GENERAL DEFINES
//**************************************
// `define DATA_WIDTH  32
`define ILEN        32
`define IALIGN      32

//**************************************
// ALU OPCODES
//**************************************
// @TODO: Redefine these values based on a more refined architecture 
//`define ALU_NOP             4'b0000
// OPCODE[2:0]  <= RISC-V FUNC3
// OPCODE[3]    <= RISC-V FUNC7[5] IF PRESENT ELSE 1'b0
// (test) OPCODE[3]    <= 1'b1 IF need two-complement, ELSE 1'b0
`define ALU_ADD     4'b0000
`define ALU_SUB     4'b1000 
`define ALU_XOR     4'b0100
`define ALU_OR      4'b0110 
`define ALU_AND     4'b0111 
`define ALU_SLL     4'b0001
`define ALU_SRL     4'b0101
`define ALU_SRA     4'b1101
`define ALU_LTS     4'b0010
`define ALU_LTU     4'b0011

hdl/admo_alu.v
/*******************************************************************************

MIT License

Copyright (c) 2021 Gustavo Ale

Permission is hereby granted, free of charge, to any person obtaining a copy
of this software and associated documentation files (the "Software"), to deal
in the Software without restriction, including without limitation the rights
to use, copy, modify, merge, publish, distribute, sublicense, and/or sell
copies of the Software, and to permit persons to whom the Software is
furnished to do so, subject to the following conditions:

The above copyright notice and this permission notice shall be included in all
copies or substantial portions of the Software.

THE SOFTWARE IS PROVIDED "AS IS", WITHOUT WARRANTY OF ANY KIND, EXPRESS OR
IMPLIED, INCLUDING BUT NOT LIMITED TO THE WARRANTIES OF MERCHANTABILITY,
FITNESS FOR A PARTICULAR PURPOSE AND NONINFRINGEMENT. IN NO EVENT SHALL THE
AUTHORS OR COPYRIGHT HOLDERS BE LIABLE FOR ANY CLAIM, DAMAGES OR OTHER
LIABILITY, WHETHER IN AN ACTION OF CONTRACT, TORT OR OTHERWISE, ARISING FROM,
OUT OF OR IN CONNECTION WITH THE SOFTWARE OR THE USE OR OTHER DEALINGS IN THE
SOFTWARE.

*******************************************************************************/

`include "admo_defs.v"

module admo_alu
(
    input   [`DATA_WIDTH-1:0]   operand_a_i,
    input   [`DATA_WIDTH-1:0]   operand_b_i,
    input   [3:0]               operator_i,
    output  [`DATA_WIDTH-1:0]   result_o
);

    reg     [`DATA_WIDTH-1:0]   result_reg;

    reg     [`DATA_WIDTH-1:0]   shift_stage_0;
    reg     [`DATA_WIDTH-1:0]   shift_stage_1;
    reg     [`DATA_WIDTH-1:0]   shift_stage_2;
    reg     [`DATA_WIDTH-1:0]   shift_stage_3;

    wire    [`DATA_WIDTH-1:0]   sub_res;

    assign sub_res = operand_a_i - operand_b_i;
    assign result_o = result_reg;

    always @(operand_a_i or operand_b_i or operator_i) 
    begin    
        case(operator_i)
            //**************************************
            // ARITHMETIC
            //**************************************
            `ALU_ADD: begin
                result_reg = (operand_a_i + operand_b_i);
            end
            `ALU_SUB: begin 
                result_reg = sub_res;
            end
            //**************************************
            // BITWISE
            //**************************************
            `ALU_AND: begin
                result_reg = operand_a_i & operand_b_i;
            end
            `ALU_OR: begin
                result_reg = operand_a_i | operand_b_i;
            end
            `ALU_XOR: begin
                result_reg = operand_a_i ^ operand_b_i;
            end
            //**************************************
            // SHIFT
            //**************************************
            // `ALU_SLL: begin
            //     result_reg = operand_a_i <<< operand_b_i;
            //     // if(operand_b_i[0] == 1'b1) begin
            //     //     shift_stage_0 = {operand_a_i[30:0],1'b0};
            //     // end else begin
            //     //     shift_stage_0 = operand_a_i;
            //     // end

            //     // if(operand_b_i[1] == 1'b1) begin
            //     //     shift_stage_1 = {shift_stage_0[29:0],2'b00};
            //     // end else begin
            //     //     shift_stage_1 = shift_stage_0;
            //     // end

            //     // if(operand_b_i[2] == 1'b1) begin
            //     //     shift_stage_2 = {shift_stage_1[27:0],4'b0000};
            //     // end else begin
            //     //     shift_stage_2 = shift_stage_1;
            //     // end

            //     // if(operand_b_i[3] == 1'b1) begin
            //     //     shift_stage_3 = {shift_stage_2[23:0],8'b00000000};
            //     // end else begin
            //     //     shift_stage_3 = shift_stage_2;
            //     // end 

            //     // // if(operand_b_i[31:5]) begin
            //     // //     result_reg = {32{1'b0}};
            //     // // end else begin 
            //     //     if(operand_b_i[4] == 1'b1) begin
            //     //         result_reg = {shift_stage_3[15:0],16'b0000000000000000};
            //     //     end else begin 
            //     //         result_reg = shift_stage_3;
            //     //     end
            //     // // end
            // end
            default: begin
                result_reg = operand_a_i;
            end
        endcase
    end


    `ifdef COCOTB_SIM
    initial begin
        $dumpfile ("../wave/admo_alu.vcd");
        $dumpvars (0, admo_alu);
        #1;
    end
    `endif

endmodule

wave/admo_alu.vcd
$date
	Sun Jul 18 00:39:07 2021
$end
$version
	Icarus Verilog
$end
$timescale
	1ps
$end
$scope module admo_alu $end
$var wire 32 ! operand_a_i [31:0] $end
$var wire 32 " operand_b_i [31:0] $end
$var wire 4 # operator_i [3:0] $end
$var wire 32 $ result_o [31:0] $end
$var wire 32 % sub_res [31:0] $end
$var reg 32 & result_reg [31:0] $end
$upscope $end
$enddefinitions $end
#0
$dumpvars
b1111111110110110001011010100110 &
b11101100101011101010111110001000 %
b1111111110110110001011010100110 $
b0 #
b1001001100101100011001110001111 "
b110110010001001110001100010111 !
$end
#1000
b10101011000100000111111110001011 $
b10101011000100000111111110001011 &
b10101011000100000111111110001011 !
b10110001001100100100110101011101 %
b11111001110111100011001000101110 "
b1010 #
#2000
b11011011111110100111111111101010 $
b11011011111110100111111111101010 &
b11011001011100100101111111001010 !
b1010101110110000010101010100000 %
b10000011100110100011010100101010 "
b110 #
#3000
b1001110001011110010100101101101 $
b1001110001011110010100101101101 &
b1100001010101001001010010011 !
b11001010001001011111101110111001 %
b1000010000001001001011011011010 "
b0 #
#4000
b10111100101011001111011100101101 $
b10111100101011001111011100101101 &
b10111100101011001111011100101101 !
b10111001101000110010110001001110 %
b11000010011100101011011111 "
b1101 #
#5000
b10101110101000111001000011001010 $
b10101110101000111001000011001010 &
b1110001000100100100000101010001 !
b110011100000001111000111011000 %
b111101100100010100111101111001 "
b0 #
#6000
b10100011011011111111111111110101 $
b10100011011011111111111111110101 &
b10000000001001011000111101100101 !
b1011100110110100001100111010101 %
b100011010010110111010110010000 "
b110 #
#7000
b11110111000010100011001000110001 $
b11110111000010100011001000110001 &
b11110111000010100011001000110001 !
b1110111111010000001001110111001 %
b1111111001000100001111001111000 "
b1001 #
#8000
b10000111100010000100101001100010 $
b10000111100010000100101001100010 &
b10000111100010000100101001100010 !
b10000011100011111100000100111100 %
b11111110001000100100100110 "
b1101 #
#9000
b10010011000000011010100100100111 $
b10010011000000011010100100100111 &
b10010011000000011010100100100111 !
b110100000011000100110011110111 %
b1011110111101010101110000110000 "
b10 #
#10000
b10100100101111000111001011010001 $
b10100100101111000111001011010001 &
b10100100101111000111001011010001 !
b1001001011111011010000110000110 %
b1011011001111101101000101001011 "
b1111 #
#11000
b101001100010010010101010101000 $
b101001100010010010101010101000 &
b101001100010010010101010101000 !
b11001110000001001000101101110000 %
b1011011100001001001111100111000 "
b101 #
#12000
b10111001110110101011110111101111 $
b10111001110110101011110111101111 &
b111001110110100010010000101001 !
b10110000100010011000011001100011 %
b10001001010100001001110111000110 "
b110 #
#13000
b11001101000000111101111110110101 $
b11001101000000111101111110110101 &
b11001101000000111101111110110101 !
b110011111100000101000100010010 %
b10011001000100111000111010100011 "
b11 #
#14000
b110010110100111010100010010001 $
b110010110100111010100010010001 &
b11011001011101111011011000111000 !
b11101101110100111001011110001111 %
b11101011101001000001111010101001 "
b100 #
#15000
b11011100000011111010011100100101 $
b11011100000011111010011100100101 &
b10101101010110111101111000110 !
b11011100000011111010011100100101 %
b111001100110111101010010100001 "
b1000 #
#16000
b11101100100110101100101000010010 $
b11101100100110101100101000010010 &
b1100100001010010110000011111011 !
b11011011011101011011011000010010 %
b10001000101100111010101011101001 "
b100 #
#17000
b11111101100010100000101010100001 $
b11111101100010100000101010100001 &
b11111101100010100000101010100001 !
b1011011100110101110001010100110 %
b10100001111011110010011111111011 "
b1 #
#18000
b101101101011101101101101000111 $
b101101101011101101101101000111 &
b101101101011101101101101000111 !
b1000110011111011111100100101100 %
b11100111001100001110001000011011 "
b1011 #
#19000
b10100001101010110101000011111010 $
b10100001101010110101000011111010 &
b10100001101010110101000011111010 !
b10001011011110010011000001000001 %
b10110001100100010000010111001 "
b1101 #
#20000
b10001100010010011010111011010001 $
b10001100010010011010111011010001 &
b10001100010010011010111011010001 !
b10101001111101011001111011101010 %
b11100010010101000000111111100111 "
b11 #
#21000
b1010101011111010000101101000010 $
b1010101011111010000101101000010 &
b1010101011111010000101101000010 !
b10001110100001000100001101011111 %
b11000110111110001100011111100011 "
b1100 #
#22000
b111101111110100110000110100100 $
b111101111110100110000110100100 &
b111101111110100110000110100100 !
b11011110001001000001110011100100 %
b1011111110101100100010011000000 "
b1011 #
#23000
b1110100100110001011010011111011 $
b1110100100110001011010011111011 &
b1100000101000111001010010101101 !
b1001100101011100111010001011111 %
b10011111101010010000001001110 "
b0 #
#24000
b11111110101110000111100100000101 $
b11111110101110000111100100000101 &
b11111110101110000111100100000101 !
b1100100001000110000110111101000 %
b10011010100101010110101100011101 "
b10 #
#25000
b1000001100010000100011101010 $
b1000001100010000100011101010 &
b1000001100010000100011101010 !
b11010000010010111100001001001011 %
b110111111001010100011010011111 "
b1101 #
#26000
b11100000001111101110001110101100 $
b11100000001111101110001110101100 &
b10110001100001110000111000010100 !
b11100000001111101110001110101100 %
b11010001010010000010101001101000 "
b1000 #
#27000
b1100000101110111111010110001 $
b1100000101110111111010110001 &
b1100000101110111111010110001 !
b10110011011000001100001000101111 %
b1011000101101101011110010000010 "
b1110 #
#28000
b111011000111010100011101001000 $
b111011000111010100011101001000 &
b1001001001000100101110000000111 !
b1010111001001110111000011000110 %
b11110001111110101110101101000001 "
b0 #
#29000
b101110110110111111100010011000 $
b101110110110111111100010011000 &
b100000110010011011011100100100 !
b10010101101110111010110110000 %
b1110000100100100000101110100 "
#30000
b1001010110100100111101101010100 $
b1001010110100100111101101010100 &
b1001010110100100111101101010100 !
b10110000011010100011011100101 %
b110100110001010011010001101111 "
b1010 #
#31000
b11010011100010100101001001000 $
b11010011100010100101001001000 &
b11011010111110010110111001101101 !
b10111111100001011010010000010101 %
b11011011100111100101001011000 "
b111 #
#32000
b11110101011110111000001001111001 $
b11110101011110111000001001111001 &
b11110101011110111000001001111001 !
b1000010000100101110110001101011 %
b10110011011010001001011000001110 "
b1111 #
#33000
b11000011101101110100110000111001 $
b11000011101101110100110000111001 &
b11000011101101110100110000111001 !
b110011010101111101100011111 %
b10111101010011000101000100011010 "
b1100 #
#34000
b11101110111110010100010001111011 $
b11101110111110010100010001111011 &
b11100010111011000111011111110 !
b1001001110000011101100110000001 %
b11010010100110111011010101111101 "
b0 #
#35000
b10000000000000100010000100001000 $
b10000000000000100010000100001000 &
b10101000101001101011011110011010 !
b11010001100110110101011000101101 %
b11010111000010110110000101101101 "
b111 #
#36000
b10010000100010001010100101101 $
b10010000100010001010100101101 &
b10010000100010001010100101101 !
b1010110001011100000011100001110 %
b10111011111000110000111000011111 "
b1001 #
#37000
b1101010100000100111010110001010 $
b1101010100000100111010110001010 &
b1001101000000000001110000010000 !
b101111011111011100001010010110 %
b11101100000100101100101111010 "
b0 #
#38000
b1000001100010000000110 $
b1000001100010000000110 &
b10001011111011110110000011110 !
b101101010110110010011100111000 %
b11100100001000101100010011100110 "
b111 #
#39000
b10000111011111001110110111100000 $
b10000111011111001110110111100000 &
b10000111011111001110110111100000 !
b10001100100100101010000111111000 %
b11111010111010100100101111101000 "
b1101 #
#40000
b1110100010011101010111011101011 $
b1110100010011101010111011101011 &
b11101101000001100000010111011011 !
b1100101101111010101110011001011 %
b10000111010010001010100100010000 "
b0 #
#41000
b10110010101100010111111101101101 $
b10110010101100010111111101101101 &
b10110010101100010111111101101101 !
b10010111011110010110001110010010 %
b11011001110000001101111011011 "
b1101 #
#42000
b10011111100001011010100000111111 $
b10011111100001011010100000111111 &
b10000001100101110100001101000000 !
b1100011101010001101111001000001 %
b11101111011100110010011111111 "
b0 #
#43000
b11100000011001101001010101010101 $
b11100000011001101001010101010101 &
b11100000011001101001010101010101 !
b11011001011111101110000001111010 %
b110111001111011010011011011 "
b1010 #
#44000
b10001111010110001101110011000100 $
b10001111010110001101110011000100 &
b10001111010110001101110011000100 !
b10111001101100011100101000011111 %
b11010101101001110001001010100101 "
#45000
b11001101101001111101100001100110 $
b11001101101001111101100001100110 &
b11001101101001111101100001100110 !
b10111010110110100101111101110101 %
b10010110011010111100011110001 "
b1111 #
#46000
b11101011110001111100110101011000 $
b11101011110001111100110101011000 &
b11101011110001111100110101011000 !
b11001001001110100101111011010000 %
b100010100011010110111010001000 "
b1 #
#47000
b11100111000001011111111111101010 $
b11100111000001011111111111101010 &
b1100000101001100000000010110100 !
b11011010010001100000000101111110 %
b10000110010111111111111100110110 "
b0 #
#48000
b100111010110100010010101101010 $
b100111010110100010010101101010 &
b100111010110100010010101101010 !
b11000011111011110111000000000110 %
b1100011011010101011010101100100 "
b101 #
#49000
b11010001100001100000100011100001 $
b11010001100001100000100011100001 &
b11010001100001100000100011100001 !
b1001010111101010110101111000010 %
b10000110100100001001110100011111 "
b1110 #
#50000
b11111001010000101011111010110011 $
b11111001010000101011111010110011 &
b10000101111111101101100110100100 !
b10010101110101111010010010101 %
b1110011010000111110010100001111 "
b0 #
#51000
b11011011100101111111110000110101 $
b11011011100101111111110000110101 &
b11100001110010101100011100100111 !
b11011011100101111111110000110101 %
b110001100101100101011110010 "
b1000 #
#52000
b10010110100001001010000010111110 $
b10010110100001001010000010111110 &
b10010110100001001010000010111110 !
b10111011000000001010001000111011 %
b11011011100000111111111010000011 "
b1001 #
#53000
b10001111110011010000011000000011 $
b10001111110011010000011000000011 &
b10001111110011010000011000000011 !
b11111111010011000010100011000 %
b1101111111000111000000011101011 "
b1 #
#54000
b10011010001111000101110100000010 $
b10011010001111000101110100000010 &
b10011010001111000101110100000010 !
b1100100010001000100101101111000 %
b110101111110000001000110001010 "
b1100 #
#55000
b11011101111001110110000010000110 $
b11011101111001110110000010000110 &
b11011101111001110110000010000110 !
b10100010101111011100110100101101 %
b111011001010011001001101011001 "
b101 #
#56000
b1010010011010101011111101010100 $
b1010010011010101011111101010100 &
b1010010011010101011111101010100 !
b11111011100010111001100111010111 %
b1010110110111110010010101111101 "
b1010 #
#57000
b11110000000000100101101000100 $
b11110000000000100101101000100 &
b11110000000000100101101000100 !
b11001111001001011011111110001100 %
b1001110110110101000101110111000 "
b1011 #
#58000
b10010111001010101001001100010 $
b10010111001010101001001100010 &
b111001100000101101100000 !
b10010111001010101001001100010 %
b11101110000000001011100011111110 "
b1000 #
#59000
b10011010101001101111111011011001 $
b10011010101001101111111011011001 &
b10011010101001101111111011011001 !
b11101101001011111011010111111110 %
b10101101011101110100100011011011 "
b1001 #
#60000
b10110101111101010011110100110100 $
b10110101111101010011110100110100 &
b10110101111101010011110100110100 !
b10000101111010010010011100110011 %
b110000000011000001011000000001 "
b1100 #
#61000
b1101111001011111001111000001101 $
b1101111001011111001111000001101 &
b10011000011101110101110000010110 !
b11000001101111110001101000011111 %
b11010110101110000100000111110111 "
b0 #
#62000
b10010100001111001000011001100100 $
b10010100001111001000011001100100 &
b10010100001111001000011001100100 !
b10011001101010010100101110100110 %
b11111010100100110011101010111110 "
b1 #
#63000
b1010010010101100110001111001001 $
b1010010010101100110001111001001 &
b1010010010101100110001111001001 !
b11100111010110011110000011101101 %
b1101010111111001000001011011100 "
b1010 #
#64000
b10001100011101100010010011010110 $
b10001100011101100010010011010110 &
b10001100011101100010010011010110 !
b1111100101011011110110101100010 %
b1111110010000011011101110100 "
b1111 #
#65000
b1011001110110001110111111101001 $
b1011001110110001110111111101001 &
b101000101111000100011100101110 !
b11110111100111111001111001110011 %
b110001000111001010100010111011 "
b0 #
#66000
b1001000001011011001100010110111 $
b1001000001011011001100010110111 &
b1001000001011011001100010110111 !
b101010110010000001110001001110 %
b11101011001010111110001101001 "
b1100 #
#67000
b1101010100101100111001001110111 $
b1101010100101100111001001110111 &
b10110101110000101011010111100001 !
b1101010100101100111001001110111 %
b1001011001011000100001101101010 "
b1000 #
#68000
b101000000000000000011000001 $
b101000000000000000011000001 &
b10100111101000110010100011000001 !
b1011010100100110001011111011010 %
b1001101000100000001000011100111 "
b111 #
#69000
b100010011000011011100100100010 $
b100010011000011011100100100010 &
b100010011000011011100100100010 !
b1100100000011110011100110010111 %
b10111110010100100111111110001011 "
b1001 #
#70000
b11111110011100010110000000100000 $
b11111110011100010110000000100000 &
b11111110011100010110000000100000 !
b1001000111011111101001000110111 %
b10110101100000011000110111101001 "
b11 #
#71000
b110011100010111011011000101 $
b110011100010111011011000101 &
b10111101001100101111100100000000 !
b1110011111101000111101100111011 %
b1001001001111100111110111000101 "
b0 #
#72000
b1110010100101000101101011111011 $
b1110010100101000101101011111011 &
b111100011111110101011011111101 !
b110011010100101001011111111 %
b110110000101010000001111111110 "
#73000
b10000001000101111011011000100101 $
b10000001000101111011011000100101 &
b10000001000101111011011000100101 !
b11110000001101111000110000011 %
b1100011000100001100010010100010 "
b1011 #
#74000
b11110010111000101010010101101011 $
b11110010111000101010010101101011 &
b11111110111101101100110100001101 !
b11110010111000100110010010100111 %
b1100000101000110100001100110 "
b100 #
#75000
b1000111000000000000100111100000 $
b1000111000000000000100111100000 &
b1101111110000000110100111101000 !
b11000101010111110000000000100 %
b1010111000101001000100111100100 "
b111 #
#76000
b10000010011100010001100111001111 $
b10000010011100010001100111001111 &
b10000010011100010001100111001111 !
b100010001000110100011110001000 %
b1100000010011011101001001000111 "
b1 #
#77000
b11001000111110111000011000011011 $
b11001000111110111000011000011011 &
b11001000111110111000011000011011 !
b10001111001011101010100001111100 %
b111001110011001101110110011111 "
b10 #
#78000
b11100001101111011011010011100 $
b11100001101111011011010011100 &
b11100001101111011011010011100 !
b11010000000001110110100001110001 %
b1001100001100000100111000101011 "
b1011 #
#79000
b11101010000001010100100110011101 $
b11101010000001010100100110011101 &
b11101010000001010100100110011101 !
b1110010001001111010111000001 %
b11011011110000000101001111011100 "
b1010 #
#80000
b10111001001000110111010000110010 $
b10111001001000110111010000110010 &
b10111001001000110111010000110010 !
b111010010101100101110011001 %
b10110001110110001010100010011001 "
b1111 #
#81000
b1001100010110101110001000100000 $
b1001100010110101110001000100000 &
b1001100010110101110001000100000 !
b10101011011000010100110110001101 %
b10100000111110011001010010010011 "
b1101 #
#82000
b11000111101010010000000011001011 $
b11000111101010010000000011001011 &
b11000111101010010000000011001011 !
b10011011001101110111011101010110 %
b101100011100011000100101110101 "
b1001 #
#83000
b10101001011011011100111010010100 $
b10101001011011011100111010010100 &
b10101001011011011100111010010100 !
b100011101000001111100110101010 %
b10000101110011001101010011101010 "
b10 #
#84000
b10001010110010001101111010000100 $
b10001010110010001101111010000100 &
b10001010110010001101111010000100 !
b11101010100010100100010100110101 %
b10100000001111101001100101001111 "
b1111 #
#85000
b11110101001010010111100011100101 $
b11110101001010010111100011100101 &
b11110101001010010111100011100101 !
b111011100001101100111000011110 %
b10111001101000101010101011000111 "
b10 #
#86000
b1001100110001000111001111110111 $
b1001100110001000111001111110111 &
b1001100110001000111001111110111 !
b101101001001100100001110101011 %
b11111100111100011000001001100 "
b1011 #
#87000
b1110010101111101001101000111110 $
b1110010101111101001101000111110 &
b1110010101111101001101000111110 !
b10000000011101101111010010011101 %
b11110010010001111010010110100001 "
b11 #
#88000
b1010111011001110111110101001111 $
b1010111011001110111110101001111 &
b1000001011001100100010101000111 !
b101011011001010000100000111111 %
b10110000000010011110100001000 "
b110 #
#89000
b1010100111101100000100011111111 $
b1010100111101100000100011111111 &
b1010100111101100000100011111111 !
b1111111000000101000011111101 %
b1000101000101011011100000000010 "
b1001 #
#90000
b110010111000111010110111100 $
b110010111000111010110111100 &
b110010111000111010110111100 !
b1001000111110100000111011100111 %
b10111101011000100110011011010101 "
b1 #
#91000
b10010101001110011010001011001000 $
b10010101001110011010001011001000 &
b10011100110110000001111111100110 !
b10010010111101100110001010111000 %
b1001111000011011110100101110 "
b100 #
#92000
b11011111101010001110010011010001 $
b11011111101010001110010011010001 &
b11011111101010001110010011010001 !
b1111100110000101010100010000110 %
b1100010111001100011110001001011 "
b1111 #
#93000
b10110100001010001101101101100 $
b10110100001010001101101101100 &
b10110100001010001101101101100 !
b10001101011100100001001010010000 %
b10001001000100110000100011011100 "
b1 #
#94000
b11111110011101101011010011011110 $
b11111110011101101011010011011110 &
b11111110011101101011010011011110 !
b111000101101010111100101000101 %
b11000101110000010011101110011001 "
b101 #
#95000
b1111011011110011111001111111111 $
b1111011011110011111001111111111 &
b111000011110001101001001101101 !
b11110101010001110101111010010011 %
b1000011001100010111001111011010 "
b110 #
#96000
b11100001001011001001010001010011 $
b11100001001011001001010001010011 &
b11100001001011001001010001010011 !
b11101011111010101010110111101100 %
b11110101010000011110011001100111 "
b101 #
#97000
b11110010001110001100011011100010 $
b11110010001110001100011011100010 &
b11110010001110001100011011100010 !
b1101101101111000100110111111011 %
b10000100011111000111100011100111 "
b1010 #
#98000
b10010010110011101000011000111111 $
b10010010110011101000011000111111 &
b10010010110011101000011000111111 !
b1001011000101000111100010110 %
b10001001011010111111011100101001 "
b1110 #
#99000
b1101101111010011111111010111111 $
b1101101111010011111111010111111 &
b101100110010010010111010111110 !
b10111111011001110011010010110011 %
b1101101011000011111101000001011 "
b110 #
