hdl/admo_defs.v
/*******************************************************************************

MIT License

Copyright (c) 2021 Gustavo Ale

Permission is hereby granted, free of charge, to any person obtaining a copy
of this software and associated documentation files (the "Software"), to deal
in the Software without restriction, including without limitation the rights
to use, copy, modify, merge, publish, distribute, sublicense, and/or sell
copies of the Software, and to permit persons to whom the Software is
furnished to do so, subject to the following conditions:

The above copyright notice and this permission notice shall be included in all
copies or substantial portions of the Software.

THE SOFTWARE IS PROVIDED "AS IS", WITHOUT WARRANTY OF ANY KIND, EXPRESS OR
IMPLIED, INCLUDING BUT NOT LIMITED TO THE WARRANTIES OF MERCHANTABILITY,
FITNESS FOR A PARTICULAR PURPOSE AND NONINFRINGEMENT. IN NO EVENT SHALL THE
AUTHORS OR COPYRIGHT HOLDERS BE LIABLE FOR ANY CLAIM, DAMAGES OR OTHER
LIABILITY, WHETHER IN AN ACTION OF CONTRACT, TORT OR OTHERWISE, ARISING FROM,
OUT OF OR IN CONNECTION WITH THE SOFTWARE OR THE USE OR OTHER DEALINGS IN THE
SOFTWARE.

*******************************************************************************/

//**************************************
// GENERAL DEFINES
//**************************************
// `define DATA_WIDTH  32
`define ILEN        32
`define IALIGN      32

//**************************************
// ALU OPCODES
//**************************************
// @TODO: Redefine these values based on a more refined architecture 
//`define ALU_NOP             4'b0000
// OPCODE[2:0]  <= RISC-V FUNC3
// OPCODE[3]    <= RISC-V FUNC7[5] IF PRESENT ELSE 1'b0
// (test) OPCODE[3]    <= 1'b1 IF need two-complement, ELSE 1'b0
`define ALU_ADD     4'b0000
`define ALU_SUB     4'b1000 
`define ALU_XOR     4'b0100
`define ALU_OR      4'b0110 
`define ALU_AND     4'b0111 
`define ALU_SLL     4'b0001
`define ALU_SRL     4'b0101
`define ALU_SRA     4'b1101
`define ALU_LTS     4'b0010
`define ALU_LTU     4'b0011

hdl/admo_alu.v
/*******************************************************************************

MIT License

Copyright (c) 2021 Gustavo Ale

Permission is hereby granted, free of charge, to any person obtaining a copy
of this software and associated documentation files (the "Software"), to deal
in the Software without restriction, including without limitation the rights
to use, copy, modify, merge, publish, distribute, sublicense, and/or sell
copies of the Software, and to permit persons to whom the Software is
furnished to do so, subject to the following conditions:

The above copyright notice and this permission notice shall be included in all
copies or substantial portions of the Software.

THE SOFTWARE IS PROVIDED "AS IS", WITHOUT WARRANTY OF ANY KIND, EXPRESS OR
IMPLIED, INCLUDING BUT NOT LIMITED TO THE WARRANTIES OF MERCHANTABILITY,
FITNESS FOR A PARTICULAR PURPOSE AND NONINFRINGEMENT. IN NO EVENT SHALL THE
AUTHORS OR COPYRIGHT HOLDERS BE LIABLE FOR ANY CLAIM, DAMAGES OR OTHER
LIABILITY, WHETHER IN AN ACTION OF CONTRACT, TORT OR OTHERWISE, ARISING FROM,
OUT OF OR IN CONNECTION WITH THE SOFTWARE OR THE USE OR OTHER DEALINGS IN THE
SOFTWARE.

*******************************************************************************/

`include "admo_defs.v"

module admo_alu
(
    input   [`DATA_WIDTH-1:0]   operand_a_i,
    input   [`DATA_WIDTH-1:0]   operand_b_i,
    input   [3:0]               operator_i,
    output  [`DATA_WIDTH-1:0]   result_o
);

    reg     [`DATA_WIDTH-1:0]   result_reg;

    reg     [`DATA_WIDTH-1:0]   shift_stage_0;
    reg     [`DATA_WIDTH-1:0]   shift_stage_1;
    reg     [`DATA_WIDTH-1:0]   shift_stage_2;
    reg     [`DATA_WIDTH-1:0]   shift_stage_3;
    
    wire    [`DATA_WIDTH-1:0]   sub_res;
    reg    compl_bit;


    assign sub_res = operand_a_i - operand_b_i;
    // assign compl_bit = 1'b0;
    // assign compl_bit = operand_a_i[31] & operator_i[3];

    assign result_o = result_reg;

    always @(operand_a_i or operand_b_i or operator_i) 
    begin    
        compl_bit = operand_a_i[31] & operator_i[3];
        case(operator_i)
            //**************************************
            // ARITHMETIC
            //**************************************
            `ALU_ADD: begin
                result_reg = (operand_a_i + operand_b_i);
            end

            `ALU_SUB: begin 
                result_reg = sub_res;
            end

            //**************************************
            // BITWISE
            //**************************************
            `ALU_AND: begin
                result_reg = operand_a_i & operand_b_i;
            end

            `ALU_OR: begin
                result_reg = operand_a_i | operand_b_i;
            end

            `ALU_XOR: begin
                result_reg = operand_a_i ^ operand_b_i;
            end

            //**************************************
            // SHIFT
            //**************************************
            `ALU_SLL: begin
                // result_reg = operand_a_i <<< operand_b_i;
                if(operand_b_i[0] == 1'b1) begin
                    shift_stage_0 = {operand_a_i[30:0],1'b0};
                end else begin
                    shift_stage_0 = operand_a_i;
                end

                if(operand_b_i[1] == 1'b1) begin
                    shift_stage_1 = {shift_stage_0[29:0],2'b00};
                end else begin
                    shift_stage_1 = shift_stage_0;
                end

                if(operand_b_i[2] == 1'b1) begin
                    shift_stage_2 = {shift_stage_1[27:0],4'b0000};
                end else begin
                    shift_stage_2 = shift_stage_1;
                end

                if(operand_b_i[3] == 1'b1) begin
                    shift_stage_3 = {shift_stage_2[23:0],8'b00000000};
                end else begin
                    shift_stage_3 = shift_stage_2;
                end 

                if(operand_b_i[4] == 1'b1) begin
                    result_reg = {shift_stage_3[15:0],16'b0000000000000000};
                end else begin 
                    result_reg = shift_stage_3;
                end
            end
            
            `ALU_SRL, `ALU_SRA: begin 
                if(operand_b_i[0] == 1'b1) begin
                    shift_stage_0 = {{1{compl_bit}}, operand_a_i[31:1]};
                end else begin
                    shift_stage_0 = operand_a_i;
                end

                if(operand_b_i[1] == 1'b1) begin
                    shift_stage_1 = {{2{compl_bit}}, shift_stage_0[31:2]};
                end else begin
                    shift_stage_1 = shift_stage_0;
                end

                if(operand_b_i[2] == 1'b1) begin
                    shift_stage_2 = {{4{compl_bit}}, shift_stage_1[31:4]};
                end else begin
                    shift_stage_2 = shift_stage_1;
                end

                if(operand_b_i[3] == 1'b1) begin
                    shift_stage_3 = {{8{compl_bit}}, shift_stage_2[31:8]};
                end else begin
                    shift_stage_3 = shift_stage_2;
                end

                if(operand_b_i[4] == 1'b1) begin
                    result_reg = {{16{compl_bit}}, shift_stage_3[31:16]};
                end else begin
                    result_reg = shift_stage_3;
                end
            end
            
            //**************************************
            // COMPARATOR
            //**************************************
            `ALU_LTS: begin
                result_reg = sub_res[31];
            end

            // `ALU_LTU: begin
            //     result_
            // end
            

            default: begin
                result_reg = operand_a_i;
            end
        endcase
    end


    `ifdef COCOTB_SIM
    initial begin
        $dumpfile ("../wave/admo_alu.vcd");
        $dumpvars (0, admo_alu);
        #1;
    end
    `endif

endmodule

wave/admo_alu.vcd
$date
	Sun Jul 18 22:56:58 2021
$end
$version
	Icarus Verilog
$end
$timescale
	1ps
$end
$scope module admo_alu $end
$var wire 32 ! operand_a_i [31:0] $end
$var wire 32 " operand_b_i [31:0] $end
$var wire 4 # operator_i [3:0] $end
$var wire 32 $ result_o [31:0] $end
$var wire 32 % sub_res [31:0] $end
$var reg 1 & compl_bit $end
$var reg 32 ' result_reg [31:0] $end
$var reg 32 ( shift_stage_0 [31:0] $end
$var reg 32 ) shift_stage_1 [31:0] $end
$var reg 32 * shift_stage_2 [31:0] $end
$var reg 32 + shift_stage_3 [31:0] $end
$upscope $end
$enddefinitions $end
#0
$dumpvars
bx +
bx *
bx )
bx (
b10111011100011110000000011100011 '
0&
b1001010011110101111111110011111 %
b10111011100011110000000011100011 $
b100 #
b1111100101010101100000110101010 "
b11000111001001011100000101001001 !
$end
#1000
b100011010111011111000101011101 $
b100011010111011111000101011101 '
b100011010111011111000101011101 !
b101110010110101000011001110111 %
b11110101000000110110101011100110 "
b1001 #
#2000
b11110100011010110101101100111111 $
b11110100011010110101101100111111 '
1&
b11110100011010110101101100111111 !
b11111010110110101010000101001110 %
b11111001100100001011100111110001 "
#3000
b10101010110111010001001111100 $
b10101010110111010001001111100 '
0&
b10101010110111010001001111100 !
b10010011111100101000000110011 %
b10110111010101001001001001 "
b1111 #
#4000
b1011000011010111100000000011011 $
b1011000011010111100000000011011 '
b10000000101011100010111000011100 !
b10101000111100001001110000011101 %
b11010111101111011001000111111111 "
b0 #
#5000
b111 $
b111 '
b1111010101001000100 +
b111101010100100010000011000 *
b1111010101001000100000110000111 )
b1111010101001000100000110000111 (
b1111010101001000100000110000111 !
b10101110011100101000110001011 %
b1100100110101011110111111111100 "
b101 #
#6000
b11111100010000001111010110101000 $
b11111100010000001111010110101000 '
1&
b11111100010000001111010110101000 !
b10001010101100001000001000111011 %
b1110001100100000111001101101101 "
b1111 #
#7000
b11100010010111010100011011000010 $
b11100010010111010100011011000010 '
b11100010010111010100011011000010 !
b1010011110000010110010101110110 %
b10001110100110111110000101001100 "
b1011 #
#8000
b11100011101010011101101010010001 $
b11100011101010011101101010010001 '
0&
b1011100100100000100101010011 !
b110011011110100011100000010101 %
b11011000000101111101000100111110 "
b0 #
#9000
b111001111100111111000100010000 $
b111001111100111111000100010000 '
b111001111100111111000100010000 !
b111001100111100101111011110000 %
b10101011001001000100000 "
b1001 #
#10000
b11011101101101000001010000000010 $
b11011101101101000001010000000010 '
1&
b11011101101101000001010000000010 !
b101111000010011010000100111 %
b11010111110100101101111111011011 "
b1111 #
#11000
b11101101011010100100101010111010 $
b11101101011010100100101010111010 '
b11101101011010100100101010111010 !
b11011111100110111110111101010110 %
b1101110011100101101101100100 "
b1011 #
#12000
b10010011000001011011010000000101 $
b10010011000001011011010000000101 '
0&
b1000011001111111111000101110001 !
b1110011000001011010101111111101 %
b11010000001110100100010101110100 "
b100 #
#13000
b110010010101000010110000101 $
b110010010101000010110000101 '
b110010010101000010110000101 !
b11101011111001101111011000001010 %
b11010011000111000111101111011 "
b1100 #
#14000
b11111111111111111111000000010101 $
b11111111111111111111000000010101 '
b11110000000101011011000100100011 +
b11110000000101011011000100100011 *
b11110000000101011011000100100011 )
b11000000010101101100010010001101 (
1&
b11000000010101101100010010001101 !
b10000010110011100000110011111011 %
b111101100010001011011110010010 "
b1101 #
#15000
b1011001011011110111011001011111 $
b1011001011011110111011001011111 '
0&
b10111110110110010000110101111000 !
b100100010000101010010010010001 %
b10011010100101100110100011100111 "
b0 #
#16000
b10110001011110010110001011111100 $
b10110001011110010110001011111100 '
1&
b10110001011110010110001011111100 !
b1001111010011100011000011010001 %
b1100010001010110011001000101011 "
b1001 #
#17000
b100010111010111110100100000111 $
b100010111010111110100100000111 '
0&
b100010111010111110100100000111 !
b111011011110111110010010000111 %
b11100111011100000000010010000000 "
#18000
b110011010101101000111001101 $
b110011010101101000111001101 '
b110011010101101000111001101 !
b11001111000011110110000010101011 %
b110111010110110111000100100010 "
#19000
b1011110000000011001101011011001 $
b1011110000000011001101011011001 '
b10101000000010101110011101101010 !
b10110001111111110110100110110111 %
b11110110000010110111110110110011 "
b100 #
#20000
b11010110000111110111011000111100 $
b11010110000111110111011000111100 '
b10100000001001101010100100111101 !
b1101010001011011101110000111110 %
b110101111110001100110011111111 "
b0 #
#21000
b110111011011101011000110110110 $
b110111011011101011000110110110 '
b10101011010101100100001001100001 !
b11111001111011101001100001100 %
b10001100000110000110111101010101 "
#22000
b10101011000100001101010110111000 $
b10101011000100001101010110111000 '
b10101011000100001101010110111000 !
b100111010111100101100000101111 %
b10000011101100100111110110001001 "
b11 #
#23000
b11100010100011010101101001010010 $
b11100010100011010101101001010010 '
1&
b11100010100011010101101001010010 !
b100010000011100101001010000 %
b11011110010010111001000000000010 "
b1110 #
#24000
b110001100010100011101001001111 $
b110001100010100011101001001111 '
0&
b110001100010100011101001001111 !
b10000000110101010010001011011100 %
b10110000101101010001011101110011 "
b1111 #
#25000
b10010101010101101011101000011100 $
b10010101010101101011101000011100 '
b11010001000100010100010110000110 !
b1100110010111101000011110000 %
b11000100010001010111010010010110 "
b0 #
#26000
b101110110110001001010010000000 $
b101110110110001001010010000000 '
b101110110110001001010010000000 !
b11111011010011111100011100111 %
b1111011011101001101110011001 "
b1100 #
#27000
b110001101100110010111100011000 $
b110001101100110010111100011000 '
b110001101100110010111100011000 +
b110001101100110010111100011000 *
b110001101100110010111100011000 )
b110001101100110010111100011000 (
b110001101100110010111100011000 !
b1011011011010111110010010111000 %
b11010110010001110100101001100000 "
b1101 #
#28000
b10000011101111010011010010100111 $
b10000011101111010011010010100111 '
1&
b10000011101111010011010010100111 !
b100000100111010101110011000011 %
b1100011000111111101011111100100 "
b1110 #
#29000
b1011010111010000001111100011001 $
b1011010111010000001111100011001 '
0&
b1011010111010000001111100011001 !
b1101010101101000010001111010001 %
b11110000001100111111101101001000 "
#30000
b11110100000101110110011110100111 $
b11110100000101110110011110100111 '
1&
b11110100000101110110011110100111 !
b10001000110100011110011110001110 %
b1101011010001011000000000011001 "
b1011 #
#31000
b10001100011111100010100001011011 $
b10001100011111100010100001011011 '
0&
b10001100011111100010100001011011 !
b11011110011011111011100110011111 %
b10101110000011100110111010111100 "
b11 #
#32000
b10010011001100011110000000101101 $
b10010011001100011110000000101101 '
b1011011110100010010001100010110 !
b100100011100000110010111111111 %
b110111011000001011110100010111 "
b0 #
#33000
b10011111010011010000001000101111 $
b10011111010011010000001000101111 '
b10011111010011010000001000101111 !
b1011010101011110100101101110111 %
b1000100100111011011011010111000 "
b11 #
#34000
b10000111100001001011011111010100 $
b10000111100001001011011111010100 '
b11001001001011101000010101001001 !
b1010110110000101001010111110 %
b10111110010101100011001010001011 "
b0 #
#35000
b11101101111111111111111111111010 $
b11101101111111111111111111111010 '
b1100101111111110100010111011010 !
b11011001110111010100101101111000 %
b10001100001000011111101001100010 "
b110 #
#36000
b1110111100110100000100100000100 $
b1110111100110100000100100000100 '
b1110111100110100000100100000100 !
b1110110110111110100100101000010 %
b101110101011111111000010 "
b1011 #
#37000
b1110011101100001101111101001100 $
b1110011101100001101111101001100 '
b10110110100001111100010011001011 !
b11110001010100001010100101000100 %
b11000101001101110001101110000111 "
b100 #
#38000
b100101001010101010101100 $
b100101001010101010101100 '
b100101001010101010101100 +
b100101001010101010101100 *
b1001010010101010101011001100 )
b1001010010101010101011001100 (
b10010100101010101010110011000 !
b1110011000001100010100011110011 %
b10011111100011110010110010100101 "
b101 #
#39000
b1 $
b1 '
b10000101001111100100000011101011 !
b10011110011010100010011001100110 %
b11100110110101000001101010000101 "
b10 #
#40000
b111111010001101100000011000001 $
b111111010001101100000011000001 '
b1110001110000001111011110010011 !
b100011001110101100000001000001 %
b1001110100001100011011101010010 "
b100 #
#41000
b111101010101000110011110 $
b111101010101000110011110 '
b111101010101000110011110 +
b11110101010100011001111010001101 *
b11110101010100011001111010001101 )
b11110101010100011001111010001101 (
b11110101010100011001111010001101 !
b1001110001100100111111110100101 %
b10100111000111110001111011101000 "
b101 #
#42000
b100000000001111110100000000000 $
b100000000001111110100000000000 '
b101001010101111110100000100001 !
b10000011001011111111110100000101 %
b10100110001001111110101100011100 "
b111 #
#43000
b1010100101011111010110110101111 $
b1010100101011111010110110101111 '
b1010100101011111010110110101111 !
b11001011111011111010000111001001 %
b10001000110000000000101111100110 "
b1110 #
#44000
b10101100111110101100010111110 $
b10101100111110101100010111110 '
b10101100111110101100010111110 !
b1010111101010010000001001000000 %
b10111101111101100101011001111110 "
b11 #
#45000
b1001001010000000011100011111100 $
b1001001010000000011100011111100 '
b1001001010000000011100011111100 !
b11110000100110101100111000001101 %
b1011000101001010110101011101111 "
#46000
b11001010100111001100111110000011 $
b11001010100111001100111110000011 '
1&
b11001010100111001100111110000011 !
b1001000101111000011000101101011 %
b10000001111000001001111000011000 "
b1011 #
#47000
b10110011100110100010100111010100 $
b10110011100110100010100111010100 '
b11100010100110000001000000101001 !
b10110011100110100010100111010100 %
b101110111111011110011001010101 "
b1000 #
#48000
b1 $
b1 '
0&
b1011011100110100010011000000110 !
b11011010000111000110110001010111 %
b10000001011111011011100110101111 "
b10 #
